Metadata-Version: 1.1
Name: responsys-client
Version: 0.2.2
Summary: This is an Oracle Responsys REST API client written in Python 2.7.
Home-page: https://github.com/spothero/py-responsys
Author: Nicholas Kincaid
Author-email: nbkincaid@gmail.com
License: UNKNOWN
Download-URL: https://github.com/spothero/py-responsys/tarball/0.1.8
Keywords: testing
Platform: UNKNOWN
Classifier: Programming Language :: Python :: 2.7
Classifier: Topic :: Software Development :: Libraries :: Python Modules
